anjani/__init__.py
anjani/__main__.py
anjani/action.py
anjani/command.py
anjani/core/__init__.py
anjani/core/anjani_bot.py
anjani/core/anjani_mixin_base.py
anjani/core/command_dispatcher.py
anjani/core/database_provider.py
anjani/core/event_dispatcher.py
anjani/core/metrics.py
anjani/core/plugin_extenter.py
anjani/core/sqlite_storage.py
anjani/core/telegram_bot.py
anjani/custom_plugins/__init__.py
anjani/custom_plugins/example.py
anjani/error.py
anjani/filters.py
anjani/internal_plugins/__init__.py
anjani/internal_plugins/canonical.py
anjani/internal_plugins/health.py
anjani/internal_plugins/spam_prediction.py
anjani/language/__init__.py
anjani/language/en.yml
anjani/language/id.yml
anjani/listener.py
anjani/main.py
anjani/plugin.py
anjani/plugins/__init__.py
anjani/plugins/admins.py
anjani/plugins/backups.py
anjani/plugins/debug.py
anjani/plugins/federation.py
anjani/plugins/filters.py
anjani/plugins/language.py
anjani/plugins/lockings.py
anjani/plugins/main.py
anjani/plugins/misc.py
anjani/plugins/muting.py
anjani/plugins/notes.py
anjani/plugins/purge.py
anjani/plugins/reporting.py
anjani/plugins/restriction.py
anjani/plugins/rules.py
anjani/plugins/spam_shield.py
anjani/plugins/staff_tools.py
anjani/plugins/stats.py
anjani/plugins/topic.py
anjani/plugins/users.py
anjani/plugins/welcome.py
anjani/util/__init__.py
anjani/util/async_helper.py
anjani/util/cache_limiter.py
anjani/util/config.py
anjani/util/converter.py
anjani/util/db/__init__.py
anjani/util/db/base.py
anjani/util/db/change_stream.py
anjani/util/db/client.py
anjani/util/db/client_session.py
anjani/util/db/collection.py
anjani/util/db/command_cursor.py
anjani/util/db/cursor.py
anjani/util/db/cursor_base.py
anjani/util/db/db.py
anjani/util/db/errors.py
anjani/util/db/typings.py
anjani/util/error.py
anjani/util/misc.py
anjani/util/system.py
anjani/util/tg.py
anjani/util/time.py
anjani/util/types.py
anjani-2.14.20.dist-info/LICENSE
anjani-2.14.20.dist-info/METADATA
anjani-2.14.20.dist-info/WHEEL
anjani-2.14.20.dist-info/entry_points.txt
anjani-2.14.20.dist-info/RECORD
