Metadata-Version: 2.1
Name: anjani
Version: 2.14.20
Summary: Telegram group management bot
Home-page: https://userbotindo.com/anjani
License: GPL-3.0-or-later
Keywords: chatbot,bot,python,telegram-bot,pyrogram
Author: Gaung Ramadhan
Author-email: hi@mrmiss.dev
Requires-Python: >=3.9,<4.0
Classifier: Environment :: Console
Classifier: Framework :: AsyncIO
Classifier: License :: OSI Approved :: GNU General Public License v3 or later (GPLv3+)
Classifier: Programming Language :: Python
Classifier: Programming Language :: Python :: 3
Classifier: Programming Language :: Python :: 3.9
Classifier: Programming Language :: Python :: 3.10
Classifier: Programming Language :: Python :: 3.11
Classifier: Programming Language :: Python :: 3
Classifier: Programming Language :: Python :: 3 :: Only
Classifier: Programming Language :: Python :: 3.10
Classifier: Programming Language :: Python :: 3.11
Classifier: Programming Language :: Python :: 3.9
Classifier: Topic :: Communications
Classifier: Topic :: Communications :: Chat
Provides-Extra: all
Provides-Extra: uvloop
Requires-Dist: PyYAML (>=6.0,<7.0)
Requires-Dist: TgCrypto (>=1.2.5,<2.0.0)
Requires-Dist: aiocache (>=0.12.0,<0.13.0)
Requires-Dist: aiohttp (>=3.8.4,<4.0.0)
Requires-Dist: aiopath (>=0.5.12,<0.6.0) ; python_version < "3.10"
Requires-Dist: aiopath (>=0.6.11,<0.7.0) ; python_version >= "3.10"
Requires-Dist: aiorun (>=2022.11.1,<2025.0.0)
Requires-Dist: certifi (>=2022.12.7,<2025.0.0) ; sys_platform == "windows"
Requires-Dist: colorlog (>=6.7.0,<7.0.0)
Requires-Dist: frozenlist (>=1.3.3,<2.0.0)
Requires-Dist: meval (>=2.5,<3.0)
Requires-Dist: multidict (>=6.0.4,<7.0.0)
Requires-Dist: prometheus-client (>=0.20.0,<0.21.0)
Requires-Dist: pydantic (>=2.8.2,<3.0.0)
Requires-Dist: pymongo (>=4.3.3,<5.0.0)
Requires-Dist: pyrofork (>=2.3.13,<3.0.0)
Requires-Dist: python-dotenv (>=0.21.1,<1.1.0)
Requires-Dist: typing-extensions (>=4.5.0,<5.0.0)
Requires-Dist: uvloop (>=0.17,<0.20) ; (sys_platform == "linux") and (extra == "all" or extra == "uvloop")
Requires-Dist: yarl (>=1.8.2,<2.0.0)
Project-URL: Documentation, https://userbotindo.com/anjani/docs/home
Project-URL: Repository, https://github.com/userbotindo/anjani
